LICENSE
MANIFEST.in
README.rst
requirements.txt
setup.py
lib/autoapi/__init__.py
lib/autoapi/apinode.py
lib/autoapi/sphinx.py
lib/autoapi.egg-info/PKG-INFO
lib/autoapi.egg-info/SOURCES.txt
lib/autoapi.egg-info/dependency_links.txt
lib/autoapi.egg-info/requires.txt
lib/autoapi.egg-info/top_level.txt
lib/autoapi/templates/autoapi/module.rst