Metadata-Version: 1.1
Name: autoapi
Version: 1.4.0
Summary: Automatic API reference documentation generation for Sphinx inspired by Doxygen
Home-page: https://autoapi.readthedocs.org/
Author: KuraLabs S.R.L
Author-email: info@kuralabs.io
License: UNKNOWN
Keywords: autoapi
Platform: UNKNOWN
Classifier: Development Status :: 5 - Production/Stable
Classifier: Intended Audience :: Developers
Classifier: License :: OSI Approved :: Apache Software License
Classifier: Natural Language :: English
Classifier: Operating System :: POSIX :: Linux
Classifier: Programming Language :: Python :: 2
Classifier: Programming Language :: Python :: 2.7
Classifier: Programming Language :: Python :: 3
Classifier: Programming Language :: Python :: 3.4
Classifier: Programming Language :: Python :: 3.5
